probullstats/__init__.py
probullstats/console.py
probullstats-0.2.0.dist-info/METADATA
probullstats-0.2.0.dist-info/WHEEL
probullstats-0.2.0.dist-info/entry_points.txt
probullstats-0.2.0.dist-info/RECORD
