Metadata-Version: 2.1
Name: probullstats
Version: 0.2.0
Summary: An engine to pull data from the ProBullStats API.
Author: Guy Hoozdis
Author-email: GuyHoozdis@users.noreply.github.com
Requires-Python: >=3.9,<4.0
Classifier: Programming Language :: Python :: 3
Classifier: Programming Language :: Python :: 3.9
Classifier: Programming Language :: Python :: 3.10
Classifier: Programming Language :: Python :: 3.11
Classifier: Programming Language :: Python :: 3.12
Requires-Dist: argparse (>=1.4.0,<2.0.0)
Requires-Dist: loguru (>=0.7.2,<0.8.0)
